.gitignore
CHANGELOG.md
LICENSE
README.md
requirements.txt
setup.py
docs/Makefile
docs/conf.py
docs/index.rst
docs/requirements.txt
docs/doc_/index.md
mysql2file/__init__.py
mysql2file/cli.py
mysql2file/constants.py
mysql2file/mysql_core.py
mysql2file/utils.py
mysql2file/version.py
mysql2file.egg-info/PKG-INFO
mysql2file.egg-info/SOURCES.txt
mysql2file.egg-info/dependency_links.txt
mysql2file.egg-info/entry_points.txt
mysql2file.egg-info/requires.txt
mysql2file.egg-info/top_level.txt
mysql2file.egg-info/zip-safe
tests/test_single.py